{
  "metadata": {
    "analysis_time": "2025-09-19 20:52:00",
    "total_modifications": 1,
    "layer1_passed": 0,
    "layer2_analyzed": 1,
    "processing_time": "10.3s"
  },
  "results": [
    {
      "modification_id": "M001",
      "cell": "C45",
      "column": "项目类型",
      "old_value": "目标管理",
      "new_value": "目标复盘待解决,已执行待优化",
      "layer1_result": {
        "judgment": "RISKY",
        "confidence": 80.0,
        "reason": "语义扩展"
      },
      "layer2_result": {
        "risk_level": "MEDIUM",
        "decision": "REVIEW",
        "confidence": 75,
        "reason": "修改后的值增加了复杂度，可能影响数据一致性和后续分析，需要人工确认修改意图和影响范围"
      },
      "final_decision": "REVIEW",
      "approval_required": true
    }
  ],
  "summary": {
    "approved": 0,
    "conditional": 0,
    "review_required": 1,
    "rejected": 0,
    "risk_distribution": {
      "LOW": 0,
      "MEDIUM": 0,
      "HIGH": 1,
      "CRITICAL": 0
    }
  }
}