{
  "metadata": {
    "analysis_time": "2025-09-15 18:21:36",
    "total_modifications": 1,
    "layer1_passed": 0,
    "layer2_analyzed": 1,
    "processing_time": "14.6s"
  },
  "results": [
    {
      "modification_id": "M001",
      "cell": "C5",
      "column": "项目类型",
      "old_value": "目标管理",
      "new_value": "",
      "layer1_result": {
        "judgment": "RISKY",
        "confidence": 90.0,
        "reason": "关键信息缺失"
      },
      "layer2_result": {
        "risk_level": "CRITICAL",
        "decision": "REJECT",
        "confidence": 95,
        "key_risks": [
          "项目类型完全清空会导致项目性质不明",
          "无法制定有效执行计划",
          "团队协作失去方向指引",
          "项目交付时间无法预估"
        ],
        "recommendation": "必须补充有效的项目类型值。建议：1)恢复原值 2)如确需修改应提供完整的新值 3)需同步更新相关项目文档和计划"
      },
      "final_decision": "REJECT",
      "approval_required": true
    }
  ],
  "summary": {
    "approved": 0,
    "conditional": 0,
    "review_required": 0,
    "rejected": 1,
    "risk_distribution": {
      "LOW": 0,
      "MEDIUM": 0,
      "HIGH": 0,
      "CRITICAL": 1
    }
  }
}