{
  "metadata": {
    "analysis_time": "2025-09-19 20:49:00",
    "total_modifications": 1,
    "layer1_passed": 0,
    "layer2_analyzed": 1,
    "processing_time": "5.2s"
  },
  "results": [
    {
      "modification_id": "M001",
      "cell": "H39",
      "column": "具体计划内容",
      "old_value": "小红书只能客服配置指南；提升转化专员的效能工具；",
      "new_value": "0519\n1.跨部门应知应会维度调整与补充【时限要求】\n2.各群聊做好跨部门信息回复及互动机制\n\n\n0506-",
      "layer1_result": {
        "judgment": "RISKY",
        "confidence": 80.0,
        "reason": "时限要求"
      },
      "layer2_result": {
        "risk_level": "MEDIUM",
        "decision": "REVIEW",
        "confidence": 75,
        "reason": "修改内容从具体的客服配置指南和效能工具转变为跨部门协调和时间要求，涉及范围扩大且时效性增强，需确认跨部门协调的一致性和可行性"
      },
      "final_decision": "REVIEW",
      "approval_required": true
    }
  ],
  "summary": {
    "approved": 0,
    "conditional": 0,
    "review_required": 1,
    "rejected": 0,
    "risk_distribution": {
      "LOW": 0,
      "MEDIUM": 0,
      "HIGH": 1,
      "CRITICAL": 0
    }
  }
}